scitChIP_Sep/__init__.py
scitChIP_Sep/scitChipSeparate.py
scitChIP_Sep-0.0.4.dist-info/LICENSE
scitChIP_Sep-0.0.4.dist-info/METADATA
scitChIP_Sep-0.0.4.dist-info/WHEEL
scitChIP_Sep-0.0.4.dist-info/entry_points.txt
scitChIP_Sep-0.0.4.dist-info/top_level.txt
scitChIP_Sep-0.0.4.dist-info/RECORD
