Metadata-Version: 2.1
Name: scitChIP-Sep
Version: 0.0.4
Summary: A package to make file preparation for sc-itChIP sequence files
Home-page: https://github.com/yoshihiko1218/sc-itChIP-Separator
Author: Jiayan(Yoshii) Ma
Author-email: jim095@ucsd.edu
License: MIT
Keywords: scitChIP preprocess separator package
Platform: UNKNOWN
Classifier: Programming Language :: Python :: 3
Classifier: License :: OSI Approved :: MIT License
Classifier: Operating System :: OS Independent
License-File: LICENSE
Requires-Dist: pandas (==1.3.1)
Requires-Dist: argparse (==1.4.0)
